fuzzysets/TrapezoidFuzzyNumber.py
fuzzysets/__init__.py
fuzzysets/cauchyfuzzyset.py
fuzzysets/inference.py
fuzzysets/tfn.py
fuzzysets/tnorm.py
fuzzysets/utils.py
initfuzzy-0.0.3.dist-info/licenses/LICENSE
initfuzzy-0.0.3.dist-info/METADATA
initfuzzy-0.0.3.dist-info/WHEEL
initfuzzy-0.0.3.dist-info/top_level.txt
initfuzzy-0.0.3.dist-info/RECORD
