Metadata-Version: 2.4
Name: initfuzzy
Version: 0.0.3
Summary: Pacote de inferência fuzzy
Author-email: Thiago Santos da Silva <tthiagosantos38@gmail.com>
License: MIT
Requires-Python: >=3.7
License-File: LICENSE
Requires-Dist: numpy
Requires-Dist: scipy
Requires-Dist: matplotlib
Dynamic: license-file
